secure_ec2/__init__.py
secure_ec2/main.py
secure_ec2/commands/__init__.py
secure_ec2/commands/config.py
secure_ec2/commands/launch.py
secure_ec2/src/__init__.py
secure_ec2/src/api.py
secure_ec2/src/aws.py
secure_ec2/src/base_logger.py
secure_ec2/src/constants.py
secure_ec2/src/helpers.py
secure_ec2-0.0.6.dist-info/AUTHORS.rst
secure_ec2-0.0.6.dist-info/LICENSE
secure_ec2-0.0.6.dist-info/METADATA
secure_ec2-0.0.6.dist-info/WHEEL
secure_ec2-0.0.6.dist-info/entry_points.txt
secure_ec2-0.0.6.dist-info/top_level.txt
secure_ec2-0.0.6.dist-info/RECORD
