Metadata-Version: 2.1
Name: secure-ec2
Version: 0.0.6
Summary: CLI tool that helps you to provision EC2 instances securely
Home-page: https://github.com/avishayil/secure_ec2
Author: Avishay Bar
Author-email: avishay.il@gmail.com
License: MIT license
Keywords: secure_ec2
Platform: UNKNOWN
Classifier: Development Status :: 2 - Pre-Alpha
Classifier: Intended Audience :: Developers
Classifier: License :: OSI Approved :: MIT License
Classifier: Natural Language :: English
Classifier: Programming Language :: Python :: 3
Classifier: Programming Language :: Python :: 3.6
Classifier: Programming Language :: Python :: 3.7
Classifier: Programming Language :: Python :: 3.8
Requires-Python: >=3.6
License-File: LICENSE
License-File: AUTHORS.rst
Requires-Dist: Click (==8.0.1)
Requires-Dist: boto3 (==1.17.109)
Requires-Dist: PyInquirer (==1.0.3)
Requires-Dist: requests (==2.25.1)
Requires-Dist: halo (==0.0.31)
Requires-Dist: pyperclip (==1.8.2)
Provides-Extra: develop
Requires-Dist: pytest (>=3) ; extra == 'develop'
Requires-Dist: pytest-cov (>=2.12) ; extra == 'develop'
Requires-Dist: bandit (>=1.7.0) ; extra == 'develop'
Requires-Dist: black (>=21.7b0) ; extra == 'develop'
Requires-Dist: isort (>=5.9.2) ; extra == 'develop'
Requires-Dist: flake8 (>=3.9.2) ; extra == 'develop'
Requires-Dist: moto (>=2.2.0) ; extra == 'develop'
Requires-Dist: coverage (>=5.5) ; extra == 'develop'
Requires-Dist: coverage-badge (>=1.0.1) ; extra == 'develop'
Requires-Dist: pre-commit (>=2.13.0) ; extra == 'develop'
Requires-Dist: bump2version (>=0.5.4) ; extra == 'develop'
Requires-Dist: tox (>=3.24.5) ; extra == 'develop'
Requires-Dist: Sphinx (>=4.4.0) ; extra == 'develop'
Requires-Dist: flake8-docstrings (>=1.6.0) ; extra == 'develop'
